alea_dublincore/__init__.py
alea_dublincore/document.py
alea_dublincore-0.1.0.dist-info/LICENSE
alea_dublincore-0.1.0.dist-info/METADATA
alea_dublincore-0.1.0.dist-info/WHEEL
alea_dublincore-0.1.0.dist-info/RECORD
