Metadata-Version: 2.1
Name: alea-dublincore
Version: 0.1.0
Summary: ALEA Dublin Core Metadata library with zero dependencies
Home-page: https://aleainstitute.ai/
License: MIT
Keywords: alea
Author: ALEA Institute
Author-email: hello@aleainstitute.ai
Requires-Python: >=3.10,<4.0.0
Classifier: Development Status :: 3 - Alpha
Classifier: Intended Audience :: Developers
Classifier: Intended Audience :: Science/Research
Classifier: License :: OSI Approved :: MIT License
Classifier: Operating System :: OS Independent
Classifier: Programming Language :: Python
Classifier: Programming Language :: Python :: 3
Classifier: Programming Language :: Python :: 3.10
Classifier: Programming Language :: Python :: 3.11
Classifier: Programming Language :: Python :: 3.12
Classifier: Programming Language :: Python :: 3.13
Classifier: Topic :: Scientific/Engineering :: Artificial Intelligence
Classifier: Topic :: Scientific/Engineering :: Information Analysis
Classifier: Topic :: Software Development :: Libraries :: Python Modules
Classifier: Topic :: Utilities
Project-URL: Repository, https://github.com/alea-institute/alea-dublincore
